comfydeploy/__init__.py
comfydeploy/_hooks/__init__.py
comfydeploy/_hooks/registration.py
comfydeploy/_hooks/sdkhooks.py
comfydeploy/_hooks/types.py
comfydeploy/_version.py
comfydeploy/basesdk.py
comfydeploy/deployment.py
comfydeploy/httpclient.py
comfydeploy/models/__init__.py
comfydeploy/models/components/__init__.py
comfydeploy/models/components/createrunresponse.py
comfydeploy/models/components/deploymentrunrequest.py
comfydeploy/models/components/httpmetadata.py
comfydeploy/models/components/mediaitem.py
comfydeploy/models/components/security.py
comfydeploy/models/components/validationerror.py
comfydeploy/models/components/workflowrunmodel.py
comfydeploy/models/components/workflowrunoutputmodel.py
comfydeploy/models/components/workflowrunstatus.py
comfydeploy/models/components/workflowrunwebhookbody.py
comfydeploy/models/components/workflowrunwebhookresponse.py
comfydeploy/models/errors/__init__.py
comfydeploy/models/errors/httpvalidationerror.py
comfydeploy/models/errors/sdkerror.py
comfydeploy/models/operations/__init__.py
comfydeploy/models/operations/cancel_run_run_run_id_cancel_post.py
comfydeploy/models/operations/get_run_run_run_id_get.py
comfydeploy/models/operations/queue_deployment_run_run_deployment_queue_post.py
comfydeploy/models/webhooks/__init__.py
comfydeploy/models/webhooks/run_update_request_body_webhook_post.py
comfydeploy/py.typed
comfydeploy/run.py
comfydeploy/sdk.py
comfydeploy/sdkconfiguration.py
comfydeploy/types/__init__.py
comfydeploy/types/basemodel.py
comfydeploy/utils/__init__.py
comfydeploy/utils/annotations.py
comfydeploy/utils/enums.py
comfydeploy/utils/eventstreaming.py
comfydeploy/utils/forms.py
comfydeploy/utils/headers.py
comfydeploy/utils/logger.py
comfydeploy/utils/metadata.py
comfydeploy/utils/queryparams.py
comfydeploy/utils/requestbodies.py
comfydeploy/utils/retries.py
comfydeploy/utils/security.py
comfydeploy/utils/serializers.py
comfydeploy/utils/url.py
comfydeploy/utils/values.py
comfydeploy-0.7.0.dist-info/METADATA
comfydeploy-0.7.0.dist-info/WHEEL
comfydeploy-0.7.0.dist-info/RECORD
