Metadata-Version: 2.3
Name: comfydeploy
Version: 0.7.0
Summary: Python Client SDK Generated by Speakeasy
Author: Speakeasy
Requires-Python: >=3.9
Classifier: Programming Language :: Python :: 3
Classifier: Programming Language :: Python :: 3.9
Classifier: Programming Language :: Python :: 3.10
Classifier: Programming Language :: Python :: 3.11
Classifier: Programming Language :: Python :: 3.12
Classifier: Programming Language :: Python :: 3.13
Requires-Dist: eval-type-backport (>=0.2.0)
Requires-Dist: httpx (>=0.28.1)
Requires-Dist: pydantic (>=2.10.3)
Requires-Dist: python-dateutil (>=2.8.2)
Requires-Dist: typing-inspection (>=0.4.0)
Project-URL: Repository, https://github.com/comfy-deploy/comfy-deploy-python.git
